pyxpiral/__init__.py
pyxpiral/__main__.py
pyxpiral/tests/__init__.py
pyxpiral/tests/pyxpiral_test.py
pyxpiral-2.0.10.dist-info/LICENSE
pyxpiral-2.0.10.dist-info/METADATA
pyxpiral-2.0.10.dist-info/WHEEL
pyxpiral-2.0.10.dist-info/top_level.txt
pyxpiral-2.0.10.dist-info/RECORD
