Metadata-Version: 2.1
Name: pyxpiral
Version: 2.0.10
Summary: Pyxpiral Pseudo-DataMatrix (de)coder
Home-page: http://github.com/elcodedocle/pyxpiral/
Author: elcodedocle
Author-email: gael.abadin@gmail.com
License: UNKNOWN
Platform: UNKNOWN
Classifier: Development Status :: 4 - Beta
Classifier: Environment :: Console
Classifier: Intended Audience :: Other Audience
Classifier: License :: OSI Approved :: MIT License
Classifier: Operating System :: OS Independent
Classifier: Natural Language :: English
Classifier: Operating System :: Unix
Classifier: Operating System :: Microsoft :: Windows
Classifier: Programming Language :: Python :: 3.7
Classifier: Programming Language :: Python :: 3
Requires-Python: >=3.7
Requires-Dist: numpy (==1.15.4)
Requires-Dist: pillow (>=7.1.0)
